autoselect/__init__.py
autoselect/admin.py
autoselect/apps.py
autoselect/urls.py
autoselect/views.py
autoselect/widgets.py
autoselect/templates/widgets/autocomplete_results.html
autoselect/templates/widgets/htmx_autocomplete.html
autoselect/templates/widgets/htmx_autocomplete_items.html
django_htmx_autoselect-0.1.2.dist-info/METADATA
django_htmx_autoselect-0.1.2.dist-info/WHEEL
django_htmx_autoselect-0.1.2.dist-info/top_level.txt
django_htmx_autoselect-0.1.2.dist-info/RECORD
