Metadata-Version: 2.4
Name: django-htmx-autoselect
Version: 0.1.2
Summary: A reusable Django app to display notifications.
Home-page: https://github.com/dw-liedji/django-htmx-autoselect
Author: Your Name
Author-email: liedjiwenkack@gmail.com
License: MIT
Classifier: Framework :: Django
Classifier: Programming Language :: Python
Classifier: Operating System :: OS Independent
Requires-Dist: Django>=3.2
Dynamic: author
Dynamic: author-email
Dynamic: classifier
Dynamic: description
Dynamic: description-content-type
Dynamic: home-page
Dynamic: license
Dynamic: requires-dist
Dynamic: summary
